planetary/__init__.py
planetary/craters.py
planetary/planetRad.py
planetary/planetThermo.py
planetary/planets.py
planetary/prettyPlots.py
planetary/rad.py
planetary/thermo.py
planetary-0.131.dist-info/METADATA
planetary-0.131.dist-info/WHEEL
planetary-0.131.dist-info/top_level.txt
planetary-0.131.dist-info/RECORD
