Metadata-Version: 2.1
Name: planetary
Version: 0.131
Summary: Tools for doing planetary science in Python
Home-page: http://github/phayne
Author: Paul O. Hayne
Author-email: paul.hayne@colorado.edu
License: MIT
Platform: UNKNOWN
Requires-Dist: numpy
Requires-Dist: matplotlib
